dj_cmd/__init__.py
dj_cmd/aliases.py
dj_cmd/dj.py
dj_cmd-1.0.0.dist-info/DESCRIPTION.rst
dj_cmd-1.0.0.dist-info/METADATA
dj_cmd-1.0.0.dist-info/RECORD
dj_cmd-1.0.0.dist-info/WHEEL
dj_cmd-1.0.0.dist-info/entry_points.txt
dj_cmd-1.0.0.dist-info/metadata.json
dj_cmd-1.0.0.dist-info/top_level.txt
